{"rights":[{"rightType":"Download","origin":{"originType":"Sample"},"rightStatus":"Revoked","acquiredDate":"2020-12-08T04:45:39.678Z","consumptions":[{"resourceItemType":"XraySidecar","targetEntity":{"entityType":"Device"},"startDate":"2020-12-08T04:47:02.925Z"},{"resourceItemType":"Content","targetEntity":{"entityType":"Device"},"startDate":"2020-12-08T04:46:56.419Z"}]}],"lastUpdatedDate":"2020-12-08T04:49:50.643Z","resource":{"resourceType":"KindleEBookSample","catalog":"Amazon","ASIN":"B07GVK5HW8","Product Name":"The Overdue Life of Amy Byler"},"entity":{"entityType":"Customer"}}