{"rights":[{"rightType":"Download","origin":{"originType":"PublicLibraryLending"},"rightStatus":"Expired","acquiredDate":"2021-11-03T16:14:09.510Z","consumptions":[{"resourceItemType":"XraySidecar","targetEntity":{"entityType":"Device"},"startDate":"2021-11-03T18:10:22.267Z"},{"resourceItemType":"XraySidecar","targetEntity":{"entityType":"Device"},"startDate":"2021-11-03T16:19:33.309Z"},{"resourceItemType":"LanguageLayerSidecar","targetEntity":{"entityType":"Device"},"startDate":"2021-11-03T16:19:33.291Z"},{"resourceItemType":"Content","targetEntity":{"entityType":"Device"},"startDate":"2021-11-03T16:19:18.006Z"},{"resourceItemType":"Content","targetEntity":{"entityType":"Device"}}]}],"lastUpdatedDate":"2021-11-04T03:30:02.185Z","resource":{"resourceType":"KindleEBook","catalog":"Amazon","ASIN":"B08SJQSWYM","Product Name":"The Night the Lights Went Out: A Memoir of Life After Brain Damage"},"entity":{"entityType":"Customer"}}