{"rights":[{"rightType":"Download","origin":{"originType":"PublicLibraryLending"},"rightStatus":"Expired","acquiredDate":"2018-01-03T16:06:43.939Z","consumptions":[{"resourceItemType":"Content","targetEntity":{"entityType":"Device"},"startDate":"2018-01-22T18:41:07.603Z"},{"resourceItemType":"XraySidecar","targetEntity":{"entityType":"Device"},"startDate":"2018-01-20T19:46:38.455Z"},{"resourceItemType":"LanguageLayerSidecar","targetEntity":{"entityType":"Device"},"startDate":"2018-01-16T20:24:59.801Z"},{"resourceItemType":"XraySidecar","targetEntity":{"entityType":"Device"},"startDate":"2018-01-16T20:24:56.810Z"},{"resourceItemType":"Content","targetEntity":{"entityType":"Device"},"startDate":"2018-01-16T20:24:54.016Z"},{"resourceItemType":"Content","targetEntity":{"entityType":"Device"},"startDate":"2018-01-15T22:11:46.322Z"},{"resourceItemType":"APNXSidecar","targetEntity":{"entityType":"Device"},"startDate":"2018-01-13T03:49:50.371Z"},{"resourceItemType":"LanguageLayerSidecar","targetEntity":{"entityType":"Device"},"startDate":"2018-01-10T14:49:01.865Z"},{"resourceItemType":"XraySidecar","targetEntity":{"entityType":"Device"},"startDate":"2018-01-10T14:48:30.188Z"},{"resourceItemType":"Content","targetEntity":{"entityType":"Device"},"startDate":"2018-01-09T22:49:34.197Z"}]}],"lastUpdatedDate":"2018-02-09T17:24:48.808Z","resource":{"resourceType":"KindleEBook","catalog":"Amazon","ASIN":"B01A4AXM3W","Product Name":"The Last Days of Night: A Novel"},"entity":{"entityType":"Customer"}}