{"rights":[{"rightType":"Download","origin":{"originType":"PublicLibraryLending"},"rightStatus":"Expired","acquiredDate":"2023-12-11T17:05:47.198Z","consumptions":[{"resourceItemType":"XraySidecar","targetEntity":{"entityType":"Device"},"startDate":"2023-12-11T17:06:36.414Z"},{"resourceItemType":"Content","targetEntity":{"entityType":"Device"}}]},{"rightType":"Download","origin":{"originType":"PublicLibraryLending"},"rightStatus":"Expired","acquiredDate":"2023-11-11T00:49:09.585Z","consumptions":[{"resourceItemType":"XraySidecar","targetEntity":{"entityType":"Device"},"startDate":"2023-11-12T23:37:26.419Z"},{"resourceItemType":"LanguageLayerSidecar","targetEntity":{"entityType":"Device"},"startDate":"2023-11-12T23:37:26.406Z"},{"resourceItemType":"Content","targetEntity":{"entityType":"Device"},"startDate":"2023-11-12T23:37:13.753Z"},{"resourceItemType":"XraySidecar","targetEntity":{"entityType":"Device"},"startDate":"2023-11-11T03:48:10.373Z"},{"resourceItemType":"Content","targetEntity":{"entityType":"Device"}}]}],"lastUpdatedDate":"2023-12-15T16:38:56.029Z","resource":{"resourceType":"KindleEBook","catalog":"Amazon","ASIN":"B0BR511292","Product Name":"Wellness: A Novel (Oprah's Book Club)"},"entity":{"entityType":"Customer"}}