{"rights":[{"rightType":"Download","origin":{"originType":"PublicLibraryLending"},"rightStatus":"Expired","acquiredDate":"2023-12-31T05:06:31.856Z","consumptions":[{"resourceItemType":"Content","targetEntity":{"entityType":"Device"}}]},{"rightType":"Download","origin":{"originType":"PublicLibraryLending"},"rightStatus":"Expired","acquiredDate":"2023-10-11T14:27:12.377Z","consumptions":[{"resourceItemType":"Content","targetEntity":{"entityType":"Device"}}]}],"lastUpdatedDate":"2024-01-10T05:01:57.673Z","resource":{"resourceType":"KindleEBook","catalog":"Amazon","ASIN":"B09RMQJCZJ","Product Name":"Aliss at the Fire — WINNER OF THE 2023 NOBEL PRIZE IN LITERATURE"},"entity":{"entityType":"Customer"}}