{"rights":[{"rightType":"Download","origin":{"originType":"Sample"},"rightStatus":"Revoked","acquiredDate":"2021-08-25T03:27:01.961Z","consumptions":[{"resourceItemType":"XraySidecar","targetEntity":{"entityType":"Device"},"startDate":"2021-08-25T03:27:14.090Z"},{"resourceItemType":"Content","targetEntity":{"entityType":"Device"},"startDate":"2021-08-25T03:27:04.634Z"}]}],"lastUpdatedDate":"2021-08-25T20:32:39.713Z","resource":{"resourceType":"KindleEBookSample","catalog":"Amazon","ASIN":"B072KZWHW4","Product Name":"The Manual: A Philosopher's Guide to Life"},"entity":{"entityType":"Customer"}}