{"rights":[{"rightType":"Download","origin":{"originType":"PublicLibraryLending"},"rightStatus":"Expired","acquiredDate":"2023-09-19T11:15:02.143Z","consumptions":[{"resourceItemType":"XraySidecar","targetEntity":{"entityType":"Device"},"startDate":"2023-09-28T01:24:43.578Z"},{"resourceItemType":"LanguageLayerSidecar","targetEntity":{"entityType":"Device"},"startDate":"2023-09-28T01:24:43.563Z"},{"resourceItemType":"Content","targetEntity":{"entityType":"Device"},"startDate":"2023-09-28T01:24:33.028Z"},{"resourceItemType":"XraySidecar","targetEntity":{"entityType":"Device"},"startDate":"2023-09-26T00:55:44.017Z"},{"resourceItemType":"Content","targetEntity":{"entityType":"Device"}}]}],"lastUpdatedDate":"2023-10-03T02:42:02.012Z","resource":{"resourceType":"KindleEBook","catalog":"Amazon","ASIN":"B0BQLKNTYR","Product Name":"The Last Devil to Die: A Thursday Murder Club Mystery (Thursday Murder Club Mysteries Book 4)"},"entity":{"entityType":"Customer"}}